text_embeddings/__init__.py
text_embeddings/embedder.py
text_embeddings/models/__init__.py
text_embeddings/models/base.py
text_embeddings/models/openai.py
text_embeddings/models/sentence_transformers.py
text_embeddings/preprocessing/__init__.py
text_embeddings/preprocessing/text_processor.py
text_embeddings/preprocessing/tokenizer.py
text_embeddings/utils/__init__.py
text_embeddings/utils/validation.py
text_embeddings_10d-0.1.0.dist-info/LICENSE
text_embeddings_10d-0.1.0.dist-info/METADATA
text_embeddings_10d-0.1.0.dist-info/WHEEL
text_embeddings_10d-0.1.0.dist-info/top_level.txt
text_embeddings_10d-0.1.0.dist-info/RECORD
